pygsp/__init__.py
pygsp/features.py
pygsp/learning.py
pygsp/optimization.py
pygsp/plotting.py
pygsp/reduction.py
pygsp/utils.py
pygsp/data/pointclouds/airfoil.mat
pygsp/data/pointclouds/bunny.mat
pygsp/data/pointclouds/david500.mat
pygsp/data/pointclouds/david64.mat
pygsp/data/pointclouds/logogsp.mat
pygsp/data/pointclouds/minnesota.mat
pygsp/data/pointclouds/two_moons.mat
pygsp/filters/__init__.py
pygsp/filters/abspline.py
pygsp/filters/approximations.py
pygsp/filters/expwin.py
pygsp/filters/filter.py
pygsp/filters/gabor.py
pygsp/filters/halfcosine.py
pygsp/filters/heat.py
pygsp/filters/held.py
pygsp/filters/itersine.py
pygsp/filters/mexicanhat.py
pygsp/filters/meyer.py
pygsp/filters/modulation.py
pygsp/filters/papadakis.py
pygsp/filters/rectangular.py
pygsp/filters/regular.py
pygsp/filters/simoncelli.py
pygsp/filters/simpletight.py
pygsp/filters/wave.py
pygsp/graphs/__init__.py
pygsp/graphs/_io.py
pygsp/graphs/_layout.py
pygsp/graphs/airfoil.py
pygsp/graphs/barabasialbert.py
pygsp/graphs/comet.py
pygsp/graphs/community.py
pygsp/graphs/davidsensornet.py
pygsp/graphs/difference.py
pygsp/graphs/erdosrenyi.py
pygsp/graphs/fourier.py
pygsp/graphs/fullconnected.py
pygsp/graphs/graph.py
pygsp/graphs/grid2d.py
pygsp/graphs/linegraph.py
pygsp/graphs/logo.py
pygsp/graphs/lowstretchtree.py
pygsp/graphs/minnesota.py
pygsp/graphs/path.py
pygsp/graphs/randomregular.py
pygsp/graphs/randomring.py
pygsp/graphs/ring.py
pygsp/graphs/star.py
pygsp/graphs/stochasticblockmodel.py
pygsp/graphs/swissroll.py
pygsp/graphs/torus.py
pygsp/graphs/nngraphs/__init__.py
pygsp/graphs/nngraphs/bunny.py
pygsp/graphs/nngraphs/cube.py
pygsp/graphs/nngraphs/grid2dimgpatches.py
pygsp/graphs/nngraphs/imgpatches.py
pygsp/graphs/nngraphs/nngraph.py
pygsp/graphs/nngraphs/sensor.py
pygsp/graphs/nngraphs/sphere.py
pygsp/graphs/nngraphs/twomoons.py
pygsp/tests/test_docstrings.py
pygsp/tests/test_filters.py
pygsp/tests/test_graphs.py
pygsp/tests/test_learning.py
pygsp/tests/test_plotting.py
pygsp-0.6.0.dist-info/licenses/LICENSE.txt
pygsp-0.6.0.dist-info/METADATA
pygsp-0.6.0.dist-info/WHEEL
pygsp-0.6.0.dist-info/top_level.txt
pygsp-0.6.0.dist-info/RECORD
