Metadata-Version: 2.4
Name: PyGSP
Version: 0.6.0
Summary: Graph Signal Processing in Python
Author: EPFL LTS2
Maintainer: EPFL LTS2
License: BSD
Project-URL: Homepage, https://github.com/epfl-lts2/pygsp
Project-URL: Documentation, https://pygsp.readthedocs.io
Project-URL: Download, https://pypi.org/project/PyGSP
Project-URL: Source Code, https://github.com/epfl-lts2/pygsp
Project-URL: Bug Tracker, https://github.com/epfl-lts2/pygsp/issues
Project-URL: Try It Online, https://mybinder.org/v2/gh/epfl-lts2/pygsp/master?urlpath=lab/tree/examples/playground.ipynb
Keywords: graph,signal,processing
Classifier: Development Status :: 4 - Beta
Classifier: Topic :: Scientific/Engineering
Classifier: Intended Audience :: Developers
Classifier: Intended Audience :: Education
Classifier: Intended Audience :: Science/Research
Classifier: License :: OSI Approved :: BSD License
Classifier: Operating System :: OS Independent
Classifier: Programming Language :: Python
Classifier: Programming Language :: Python :: 3
Classifier: Programming Language :: Python :: 3.7
Classifier: Programming Language :: Python :: 3.8
Classifier: Programming Language :: Python :: 3.9
Classifier: Programming Language :: Python :: 3.10
Classifier: Programming Language :: Python :: 3.11
Classifier: Programming Language :: Python :: 3.12
Requires-Python: >=3.8
License-File: LICENSE.txt
Requires-Dist: numpy
Requires-Dist: scipy
Provides-Extra: dev
Requires-Dist: networkx; extra == "dev"
Requires-Dist: scikit-image; extra == "dev"
Requires-Dist: scikit-learn; extra == "dev"
Requires-Dist: pyflann3; extra == "dev"
Requires-Dist: pyunlocbox>=0.6.1; extra == "dev"
Requires-Dist: matplotlib; extra == "dev"
Requires-Dist: pyqtgraph; extra == "dev"
Requires-Dist: PyOpenGL; extra == "dev"
Requires-Dist: PyQt6; extra == "dev"
Requires-Dist: flake8; extra == "dev"
Requires-Dist: coverage; extra == "dev"
Requires-Dist: coveralls; extra == "dev"
Requires-Dist: pytest; extra == "dev"
Requires-Dist: pytest-cov; extra == "dev"
Requires-Dist: sphinx; extra == "dev"
Requires-Dist: numpydoc; extra == "dev"
Requires-Dist: sphinxcontrib-bibtex; extra == "dev"
Requires-Dist: sphinx-gallery; extra == "dev"
Requires-Dist: memory_profiler; extra == "dev"
Requires-Dist: sphinx-rtd-theme; extra == "dev"
Requires-Dist: sphinx-copybutton; extra == "dev"
Requires-Dist: build; extra == "dev"
Requires-Dist: wheel; extra == "dev"
Requires-Dist: twine; extra == "dev"
Requires-Dist: pre-commit; extra == "dev"
Provides-Extra: test
Requires-Dist: pytest; extra == "test"
Requires-Dist: pytest-cov; extra == "test"
Requires-Dist: flake8; extra == "test"
Requires-Dist: coverage; extra == "test"
Provides-Extra: docs
Requires-Dist: sphinx; extra == "docs"
Requires-Dist: numpydoc; extra == "docs"
Requires-Dist: sphinxcontrib-bibtex; extra == "docs"
Requires-Dist: sphinx-gallery; extra == "docs"
Requires-Dist: memory_profiler; extra == "docs"
Requires-Dist: sphinx-rtd-theme; extra == "docs"
Requires-Dist: sphinx-copybutton; extra == "docs"
Provides-Extra: plot
Requires-Dist: matplotlib; extra == "plot"
Requires-Dist: pyqtgraph; extra == "plot"
Requires-Dist: PyOpenGL; extra == "plot"
Requires-Dist: PyQt6; extra == "plot"
Dynamic: license-file
